P4.py
P4API.cpython-312-darwin.so
p4python-2025.2.2863679.dist-info/licenses/LICENSE.txt
p4python-2025.2.2863679.dist-info/METADATA
p4python-2025.2.2863679.dist-info/WHEEL
p4python-2025.2.2863679.dist-info/top_level.txt
p4python-2025.2.2863679.dist-info/RECORD
