Metadata-Version: 2.4
Name: p4python
Version: 2025.2.2863679
Summary: P4Python - Python interface to Perforce API
Home-page: http://www.perforce.com
Author: Perforce Software Inc
Author-email: support@perforce.com
Maintainer: Perforce Software Inc
Maintainer-email: support@perforce.com
License: LICENSE.txt
Keywords: Perforce perforce P4Python
Classifier: Development Status :: 5 - Production/Stable
Classifier: Intended Audience :: Developers
Classifier: License :: Freely Distributable
Classifier: Programming Language :: Python
Classifier: Topic :: Software Development :: Libraries :: Python Modules
Classifier: Topic :: Software Development :: Version Control
Classifier: Topic :: Software Development
Classifier: Topic :: Utilities
Classifier: Operating System :: Microsoft :: Windows
Classifier: Operating System :: Unix
Classifier: Operating System :: MacOS :: MacOS X
License-File: LICENSE.txt
Dynamic: author
Dynamic: author-email
Dynamic: classifier
Dynamic: description
Dynamic: home-page
Dynamic: keywords
Dynamic: license
Dynamic: license-file
Dynamic: maintainer
Dynamic: maintainer-email
Dynamic: summary
